patent_extractor/__init__.py
patent_extractor/patent_extractor.py
patent_extractor-0.2.0.dist-info/METADATA
patent_extractor-0.2.0.dist-info/WHEEL
patent_extractor-0.2.0.dist-info/entry_points.txt
patent_extractor-0.2.0.dist-info/top_level.txt
patent_extractor-0.2.0.dist-info/RECORD
